onnx_asr/__init__.py
onnx_asr/adapters.py
onnx_asr/asr.py
onnx_asr/cli.py
onnx_asr/loader.py
onnx_asr/onnx.py
onnx_asr/py.typed
onnx_asr/utils.py
onnx_asr/vad.py
onnx_asr/models/__init__.py
onnx_asr/models/gigaam.py
onnx_asr/models/kaldi.py
onnx_asr/models/nemo.py
onnx_asr/models/pyannote.py
onnx_asr/models/silero.py
onnx_asr/models/tone.py
onnx_asr/models/whisper.py
onnx_asr/preprocessors/__init__.py
onnx_asr/preprocessors/gigaam_v2.onnx
onnx_asr/preprocessors/gigaam_v3.onnx
onnx_asr/preprocessors/kaldi.onnx
onnx_asr/preprocessors/kaldi_fast.onnx
onnx_asr/preprocessors/nemo128.onnx
onnx_asr/preprocessors/nemo80.onnx
onnx_asr/preprocessors/preprocessor.py
onnx_asr/preprocessors/resample_11_16.onnx
onnx_asr/preprocessors/resample_11_8.onnx
onnx_asr/preprocessors/resample_16_8.onnx
onnx_asr/preprocessors/resample_22_16.onnx
onnx_asr/preprocessors/resample_22_8.onnx
onnx_asr/preprocessors/resample_24_16.onnx
onnx_asr/preprocessors/resample_24_8.onnx
onnx_asr/preprocessors/resample_32_16.onnx
onnx_asr/preprocessors/resample_32_8.onnx
onnx_asr/preprocessors/resample_44_16.onnx
onnx_asr/preprocessors/resample_44_8.onnx
onnx_asr/preprocessors/resample_48_16.onnx
onnx_asr/preprocessors/resample_48_8.onnx
onnx_asr/preprocessors/resample_8_16.onnx
onnx_asr/preprocessors/resampler.py
onnx_asr/preprocessors/whisper128.onnx
onnx_asr/preprocessors/whisper80.onnx
onnx_asr-0.10.2.dist-info/METADATA
onnx_asr-0.10.2.dist-info/WHEEL
onnx_asr-0.10.2.dist-info/entry_points.txt
onnx_asr-0.10.2.dist-info/licenses/LICENSE
onnx_asr-0.10.2.dist-info/RECORD
