Metadata-Version: 2.4
Name: onnx-asr
Version: 0.10.2
Summary: A lightweight Python package for Automatic Speech Recognition using ONNX models
Project-URL: Documentation, https://istupakov.github.io/onnx-asr
Project-URL: Release notes, https://github.com/istupakov/onnx-asr/releases
Project-URL: Issues, https://github.com/istupakov/onnx-asr/issues
Project-URL: Source, https://github.com/istupakov/onnx-asr
Author-email: Ilya Stupakov <istupakov@gmail.com>
License-Expression: MIT
License-File: LICENSE
Keywords: asr,onnx,speech-recognition,speech-to-text,stt
Classifier: Development Status :: 4 - Beta
Classifier: Intended Audience :: Developers
Classifier: Intended Audience :: Education
Classifier: Intended Audience :: Science/Research
Classifier: Operating System :: OS Independent
Classifier: Programming Language :: Python
Classifier: Programming Language :: Python :: 3 :: Only
Classifier: Programming Language :: Python :: 3.10
Classifier: Programming Language :: Python :: 3.11
Classifier: Programming Language :: Python :: 3.12
Classifier: Programming Language :: Python :: 3.13
Classifier: Programming Language :: Python :: 3.14
Classifier: Programming Language :: Python :: Free Threading :: 2 - Beta
Classifier: Topic :: Multimedia :: Sound/Audio :: Speech
Classifier: Topic :: Scientific/Engineering
Classifier: Topic :: Scientific/Engineering :: Artificial Intelligence
Classifier: Typing :: Typed
Requires-Python: >=3.10
Requires-Dist: numpy>=1.21.6
Requires-Dist: typing-extensions>=4.15.0; python_version < '3.11'
Provides-Extra: cpu
Requires-Dist: onnxruntime>=1.18.1; extra == 'cpu'
Provides-Extra: gpu
Requires-Dist: onnxruntime-gpu>=1.18.1; extra == 'gpu'
Provides-Extra: hub
Requires-Dist: huggingface-hub>=0.30.2; extra == 'hub'
